ialib/__init__.py
ialib/back_testing.py
ialib/bottle_client.py
ialib/data_ops.py
ialib/genie_metalanguage.py
ialib/genome_info.py
ialib/prediction_models.py
ialib/tests/__init__.py
ialib/tests/classification.py
ialib/tests/utility.py
ia_genie_sdk-0.1.30.dist-info/METADATA
ia_genie_sdk-0.1.30.dist-info/WHEEL
ia_genie_sdk-0.1.30.dist-info/top_level.txt
ia_genie_sdk-0.1.30.dist-info/RECORD
