Metadata-Version: 2.1
Name: ia-genie-sdk
Version: 0.1.30
Summary: SDK for Intelligent Artifact's Genie, a general evolving networked intelligence engine using GAIuS framework.
Home-page: https://bitbucket.org/intelligent-artifacts/geniesdk-python/src/master/
Author: Intelligent Artifacts
Author-email: support@intelligent-artifacts.com
License: UNKNOWN
Platform: UNKNOWN
Classifier: Programming Language :: Python :: 3
Classifier: License :: OSI Approved :: MIT License
Classifier: Operating System :: OS Independent
Requires-Dist: requests
Requires-Dist: pymongo
